{"spec": {"description": "A scatterplot showing horsepower and miles per gallons.", "mark": "point", "$schema": "https://vega.github.io/schema/vega-lite/v1.2.1.json", "data": {"url": "https://vega.github.io/vega-lite/data/cars.json"}, "encoding": {"color": {"type": "nominal", "field": "Origin"}, "x": {"type": "quantitative", "field": "Horsepower"}, "shape": {"type": "nominal", "field": "Origin"}, "y": {"type": "quantitative", "field": "Miles_per_Gallon"}}}, "mode": "vega-lite", "actions": {"export": true, "source": true, "editor": true}}