{"mode": "vega-lite", "actions": {"export": false, "editor": true, "source": false}, "spec": {"encoding": {"color": {"scale": {"domain": ["sun", "fog", "drizzle", "rain", "snow"], "range": ["#e7ba52", "#c7c7c7", "#aec7e8", "#1f77b4", "#9467bd"]}, "type": "nominal", "legend": {"title": "Weather type"}, "field": "weather"}, "y": {"type": "quantitative", "aggregate": "count", "field": "*"}, "x": {"timeUnit": "month", "type": "temporal", "axis": {"title": "Month of the year"}, "field": "date"}}, "mark": "bar", "data": {"url": "http://vega.github.io/vega-lite/data/seattle-weather.csv", "formatType": "csv"}}}