{"spec": {"transform": {"calculate": [{"expr": "datum.Origin[0]", "field": "OriginInitial"}]}, "encoding": {"color": {"type": "nominal", "field": "Origin"}, "text": {"type": "nominal", "field": "OriginInitial"}, "x": {"type": "quantitative", "field": "Horsepower"}, "y": {"type": "quantitative", "field": "Miles_per_Gallon"}}, "mark": "text", "$schema": "https://vega.github.io/schema/vega-lite/v1.2.1.json", "data": {"url": "https://vega.github.io/vega-lite/data/cars.json"}}, "mode": "vega-lite", "actions": {"export": true, "source": true, "editor": true}}